{
  "summerTours": [
    {
      "id": 101,
      "tourName": "Simla",
      "cost": 25000
    },
    {
      "id": 102,
      "tourName": "Ooty",
      "cost": 5000
    },
    {
      "id": 103,
      "tourName": "Munnar",
      "cost": 15000
    },
    {
      "id": 104,
      "tourName": "Pondy",
      "cost": 3000
    },
    {
      "id": "105",
      "tourName": "Nainital",
      "cost": "14000"
    },
    {
      "id": "108",
      "tourName": "jammu",
      "cost": "34"
    },
    {
      "id": "110",
      "tourName": "mahab",
      "cost": "34"
    },
    {
      "id": "455",
      "tourName": "dfdfd",
      "cost": "33"
    },
    {
      "id": "44",
      "tourName": "dsdfs",
      "cost": "2323"
    },
    {
      "id": "344",
      "tourName": "dsdfds",
      "cost": "333"
    },
    {
      "id": "3434",
      "tourName": "dfsdf",
      "cost": "4444"
    },
    {
      "id": "0555",
      "tourName": "cbvcbvcb",
      "cost": "788"
    },
    {
      "id": "999",
      "tourName": "22ddfd",
      "cost": "ddfd"
    },
    {
      "id": "666",
      "tourName": "ddd",
      "cost": "66"
    },
    {
      "id": "8999",
      "tourName": "jjjdjdj",
      "cost": "45"
    },
    {
      "id": "45",
      "tourName": "kk",
      "cost": "566"
    },
    {
      "id": "4555",
      "tourName": "kkggg",
      "cost": "56688"
    },
    {
      "id": "444230",
      "tourName": "sdfsdfd",
      "cost": "66"
    },
    {
      "id": "44423044",
      "tourName": "sdfsdfd444",
      "cost": "6666"
    },
    {
      "id": "884858",
      "tourName": "Pune",
      "cost": "5858"
    },
    {
      "id": "84848",
      "tourName": "Tirumala",
      "cost": "44"
    },
    {
      "id": "999343",
      "tourName": "shirdi",
      "cost": "899"
    },
    {
      "id": "89990",
      "tourName": "vellore",
      "cost": "788"
    }
  ],
  "agents": [
    {
      "id": 201,
      "name": "Siva",
      "phoneNumber": 9125010
    },
    {
      "id": 202,
      "name": "Guna",
      "phoneNumber": 89010201
    },
    {
      "id": 203,
      "name": "Giri",
      "phoneNumber": 79010201
    },
    {
      "id": 204,
      "name": "Vivek",
      "phoneNumber": 69010201
    }
  ],
  "employees": []
}